enan/__init__.py
enan/analyzer.py
enan/binom.py
enan/connect.py
enan/fet.py
enan/gsea.py
enan/ssgsea.py
enan/calculator/__init__.py
enan/calculator/_binom.py
enan/calculator/_connectivity.py
enan/calculator/_fet.py
enan/calculator/_gsea.py
enan/data/__init__.py
enan/data/adjuster.py
enan/data/data.py
enan/data/data_control.py
enan/plot/__init__.py
enan/plot/_plot.py
enan/process/__init__.py
enan/process/processor.py
enan-1.0.4.dist-info/LICENSE.txt
enan-1.0.4.dist-info/METADATA
enan-1.0.4.dist-info/WHEEL
enan-1.0.4.dist-info/top_level.txt
enan-1.0.4.dist-info/RECORD
